UtilityLibAPI/Archive7zLib.cp310-win_amd64.pyd
UtilityLibAPI/Archive7zLib.pyi
UtilityLibAPI/EnDeCodeCppPyLib.cp310-win_amd64.pyd
UtilityLibAPI/EnDeCodeCppPyLib.pyi
UtilityLibAPI/EnDeCodeLib.cp310-win_amd64.pyd
UtilityLibAPI/EnDeCodeLib.pyi
UtilityLibAPI/ExtWrapper7zLib.cp310-win_amd64.pyd
UtilityLibAPI/ExtWrapper7zLib.pyi
UtilityLibAPI/MailSenderLib.cp310-win_amd64.pyd
UtilityLibAPI/MailSenderLib.pyi
UtilityLibAPI/SessionVARLib.cp310-win_amd64.pyd
UtilityLibAPI/SessionVARLib.pyi
UtilityLibAPI/__init__.py
UtilityLibAPI/out/UtilityLibAPI/Archive7zLib.pyi
UtilityLibAPI/out/UtilityLibAPI/EnDeCodeCppPyLib.pyi
UtilityLibAPI/out/UtilityLibAPI/EnDeCodeLib.pyi
UtilityLibAPI/out/UtilityLibAPI/ExtWrapper7zLib.pyi
UtilityLibAPI/out/UtilityLibAPI/MailSenderLib.pyi
UtilityLibAPI/out/UtilityLibAPI/SessionVARLib.pyi
utilitylibapi-1.2601.3003.dist-info/licenses/LICENSE
utilitylibapi-1.2601.3003.dist-info/METADATA
utilitylibapi-1.2601.3003.dist-info/WHEEL
utilitylibapi-1.2601.3003.dist-info/top_level.txt
utilitylibapi-1.2601.3003.dist-info/RECORD
