Metadata-Version: 2.4
Name: UtilityLibAPI
Version: 1.2601.3003
Summary: UtilityLibAPI Python package
Author-email: James Lin <tylin123@ms27.hinet.net>
License: Copyright (c) 2025 James Lin **UtilityLibAPI**
Project-URL: Homepage, https://mis.gotech.biz
License-File: LICENSE
Requires-Dist: pymysql
Dynamic: license-file
